probabilistic_functions/__init__.py
probabilistic_functions/core.py
probabilistic_functions/cure.py
probabilistic_functions/metrics.py
probabilistic_functions/plots.py
probabilistic_functions/plots2.py
probabilistic_functions/prueba.py
probabilistic_functions/utils.py
probabilistic_functions/functions/Birnbaum_Saunders.py
probabilistic_functions/functions/Burr.py
probabilistic_functions/functions/Exponential.py
probabilistic_functions/functions/Gamma.py
probabilistic_functions/functions/Gumbel.py
probabilistic_functions/functions/Inverse_Weibull.py
probabilistic_functions/functions/Lindley.py
probabilistic_functions/functions/LogNorm.py
probabilistic_functions/functions/Nadarajah_Haghighi.py
probabilistic_functions/functions/Norm.py
probabilistic_functions/functions/Pareto.py
probabilistic_functions/functions/Rayleigh.py
probabilistic_functions/functions/Weibull.py
probabilistic_functions/functions/Weibull_3Params.py
probabilistic_functions/functions/__init__.py
probabilistic_functions-0.6.0.dist-info/licenses/LICENSE
probabilistic_functions-0.6.0.dist-info/METADATA
probabilistic_functions-0.6.0.dist-info/WHEEL
probabilistic_functions-0.6.0.dist-info/top_level.txt
probabilistic_functions-0.6.0.dist-info/RECORD
