Metadata-Version: 2.4
Name: probabilistic_functions
Version: 0.6.0
Summary: A Python package for working with probabilistic functions and distributions.
Author: Wilhelm David Buitrago Garcia
Project-URL: Homepage, https://github.com/WilhelmBuitrago/probabilistic-functions.git
Project-URL: documentation, https://github.com/WilhelmBuitrago/probabilistic-functions/blob/main/CHANGELOG.md
Keywords: probability,functions,distributions,statistics,notebooks,jupyter
Classifier: Development Status :: 3 - Alpha
Classifier: Operating System :: OS Independent
Classifier: Programming Language :: Python :: 3
Classifier: Programming Language :: Python :: 3.13
Requires-Python: >=3.13
License-File: LICENSE
Requires-Dist: sympy>=1.14.0
Requires-Dist: matplotlib>=3.10.3
Dynamic: license-file
